README.md
setup.py
vmaas_report/__init__.py
vmaas_report/evaluator.py
vmaas_report/main.py
vmaas_report/rpm_backend.py
vmaas_report/vmaas_api.py
vmaas_report.egg-info/PKG-INFO
vmaas_report.egg-info/SOURCES.txt
vmaas_report.egg-info/dependency_links.txt
vmaas_report.egg-info/entry_points.txt
vmaas_report.egg-info/requires.txt
vmaas_report.egg-info/top_level.txt