Metadata-Version: 1.2
Name: vmaas-report
Version: 0.1.9
Summary: A tool for getting vulnerabilities from VMaaS for given system package profile
Home-page: https://github.com/jdobes/vmaas-report
Author: Jan Dobes
Author-email: jdobes@redhat.com
License: MIT
Platform: UNKNOWN
Requires-Python: >=2.6
